[
    {
        "qid": "438671021",
        "image": "COCO_train2014_000000438671.jpg",
        "question": "What sits on the left hand side of the bowl?",
        "src_dataset": "VQA",
        "answers": [
            "jug",
            "milk",
            "cup",
            "container",
            "eggs",
            "spoon",
            "bottle",
            "broccoli",
            "milk",
            "grapes"
        ],
        "ans_diff_labels": [
            0,
            2,
            0,
            1,
            5,
            1,
            3,
            4,
            0,
            0
        ],
        "kmeans_score": 90.88888888888889,
        "inertia": 0.0,
        "penalty": 88.88888888888889,
        "difference_penalty": 2.0,
        "num_clusters": 9.0,
        "ans_groups": [
            8,
            1,
            7,
            5,
            6,
            4,
            0,
            2,
            1,
            3
        ]
    },
    {
        "qid": "439926000",
        "image": "COCO_train2014_000000439926.jpg",
        "question": "What team is the player in white on?",
        "src_dataset": "VQA",
        "answers": [
            "orioles",
            "orioles",
            "orioles",
            "orioles",
            "orion",
            "orioles",
            "orioles",
            "orioles",
            "oros",
            "birds"
        ],
        "ans_diff_labels": [
            0,
            1,
            0,
            0,
            5,
            1,
            3,
            3,
            0,
            0
        ],
        "kmeans_score": 71.33333333333334,
        "inertia": 4.644801358065154e-31,
        "penalty": 33.333333333333336,
        "difference_penalty": 38.0,
        "num_clusters": 4.0,
        "ans_groups": [
            0,
            0,
            0,
            0,
            1,
            0,
            0,
            0,
            2,
            3
        ]
    },
    {
        "qid": "441379002",
        "image": "COCO_train2014_000000441379.jpg",
        "question": "What do these animals have strapped to their backs?",
        "src_dataset": "VQA",
        "answers": [
            "coats",
            "coats",
            "coats",
            "shirts",
            "jackets",
            "toys",
            "tiny horses",
            "teddy bears",
            "teddy bears",
            "stuffed animals"
        ],
        "ans_diff_labels": [
            0,
            0,
            0,
            0,
            4,
            1,
            3,
            1,
            0,
            0
        ],
        "kmeans_score": 73.9492262028707,
        "inertia": 25.50478175842626,
        "penalty": 44.44444444444444,
        "difference_penalty": 4.0,
        "num_clusters": 5.0,
        "ans_groups": [
            3,
            3,
            3,
            0,
            0,
            4,
            1,
            2,
            2,
            1
        ]
    },
    {
        "qid": "439506005",
        "image": "COCO_train2014_000000439506.jpg",
        "question": "Does the girl dye her hair?",
        "src_dataset": "VQA",
        "answers": [
            "no",
            "no",
            "no",
            "maybe",
            "no",
            "no",
            "no",
            "no",
            "yes",
            "yes"
        ],
        "ans_diff_labels": [
            1,
            0,
            0,
            1,
            4,
            1,
            2,
            1,
            0,
            0
        ],
        "kmeans_score": 39.768692425336326,
        "inertia": 8.657581314225217,
        "penalty": 11.11111111111111,
        "difference_penalty": 20.0,
        "num_clusters": 2.0,
        "ans_groups": [
            0,
            0,
            0,
            1,
            0,
            0,
            0,
            0,
            1,
            1
        ]
    },
    {
        "qid": "442150001",
        "image": "COCO_train2014_000000442150.jpg",
        "question": "Where are the flowers?",
        "src_dataset": "VQA",
        "answers": [
            "behind her",
            "on edge of counter",
            "left",
            "left",
            "behind person",
            "vase",
            "behind girl",
            "in vase",
            "on counter",
            "floor"
        ],
        "ans_diff_labels": [
            0,
            0,
            0,
            1,
            5,
            0,
            3,
            1,
            0,
            0
        ],
        "kmeans_score": 70.33504918314819,
        "inertia": 21.89060473870375,
        "penalty": 44.44444444444444,
        "difference_penalty": 4.0,
        "num_clusters": 5.0,
        "ans_groups": [
            0,
            3,
            2,
            2,
            0,
            1,
            0,
            1,
            3,
            4
        ]
    },
    {
        "qid": "442150001",
        "image": "COCO_train2014_000000442150.jpg",
        "question": "Where are the flowers?",
        "src_dataset": "VQA",
        "answers": [
            "behind her",
            "on edge of counter",
            "left",
            "left",
            "behind person",
            "vase",
            "behind girl",
            "in vase",
            "on counter",
            "floor"
        ],
        "ans_diff_labels": [
            0,
            0,
            0,
            1,
            5,
            0,
            3,
            1,
            0,
            0
        ],
        "kmeans_score": 70.33504918314819,
        "inertia": 21.89060473870375,
        "penalty": 44.44444444444444,
        "difference_penalty": 4.0,
        "num_clusters": 5.0,
        "ans_groups": [
            0,
            3,
            2,
            2,
            0,
            1,
            0,
            1,
            3,
            4
        ]
    },
    {
        "qid": "436981000",
        "image": "COCO_train2014_000000436981.jpg",
        "question": "What are the letters on the bus?",
        "src_dataset": "VQA",
        "answers": [
            "lak309g",
            "lak",
            "lak",
            "3096",
            "lak",
            "lak",
            "lak 3090",
            "lak",
            "lak",
            "lak309g"
        ],
        "ans_diff_labels": [
            0,
            0,
            0,
            0,
            5,
            1,
            3,
            4,
            0,
            0
        ],
        "kmeans_score": 40.6315095612364,
        "inertia": 17.520398450125292,
        "penalty": 11.11111111111111,
        "difference_penalty": 12.0,
        "num_clusters": 2.0,
        "ans_groups": [
            1,
            1,
            0,
            1,
            1,
            0,
            1,
            1
        ]
    },
    {
        "qid": "441678001",
        "image": "COCO_train2014_000000441678.jpg",
        "question": "Where is the silverware?",
        "src_dataset": "VQA",
        "answers": [
            "no",
            "there isn't any",
            "don't know!",
            "not on table",
            "in someone's hand",
            "gone",
            "absent",
            "gone",
            "there is none shown",
            "in drawer"
        ],
        "ans_diff_labels": [
            0,
            2,
            2,
            1,
            3,
            0,
            2,
            1,
            0,
            0
        ],
        "kmeans_score": 80.0127768256822,
        "inertia": 25.568332381237752,
        "penalty": 44.44444444444444,
        "difference_penalty": 10.0,
        "num_clusters": 5.0,
        "ans_groups": [
            1,
            1,
            2,
            1,
            4,
            3,
            0,
            3,
            1,
            4
        ]
    },
    {
        "qid": "443607008",
        "image": "COCO_train2014_000000443607.jpg",
        "question": "What is the man looking out of?",
        "src_dataset": "VQA",
        "answers": [
            "carriage",
            "wagon",
            "buggy",
            "glasses",
            "buggy",
            "eyes",
            "he's looking out his eyes",
            "wagon",
            "horse carriage",
            "tree"
        ],
        "ans_diff_labels": [
            0,
            0,
            0,
            0,
            5,
            0,
            4,
            2,
            0,
            0
        ],
        "kmeans_score": 77.53121318524586,
        "inertia": 13.975657629690309,
        "penalty": 55.55555555555556,
        "difference_penalty": 8.0,
        "num_clusters": 6.0,
        "ans_groups": [
            1,
            3,
            2,
            4,
            2,
            0,
            0,
            3,
            1,
            5
        ]
    },
    {
        "qid": "441633001",
        "image": "COCO_train2014_000000441633.jpg",
        "question": "What type of hat is this man wearing?",
        "src_dataset": "VQA",
        "answers": [
            "hat with hole",
            "fedora",
            "bucket hat",
            "rasta hat",
            "ponytail",
            "fedora with dreads",
            "visor",
            "fedora",
            "visor",
            "top"
        ],
        "ans_diff_labels": [
            0,
            0,
            0,
            0,
            5,
            0,
            3,
            2,
            0,
            0
        ],
        "kmeans_score": 79.21509079745864,
        "inertia": 6.548424130791973,
        "penalty": 66.66666666666667,
        "difference_penalty": 6.0,
        "num_clusters": 7.0,
        "ans_groups": [
            1,
            2,
            1,
            6,
            3,
            5,
            0,
            2,
            0,
            4
        ]
    },
    {
        "qid": "440689009",
        "image": "COCO_train2014_000000440689.jpg",
        "question": "What is on the front of the bike?",
        "src_dataset": "VQA",
        "answers": [
            "mirrors",
            "mirrors",
            "motorcycle",
            "mirrors",
            "another bike",
            "mirrors",
            "mirror",
            "tire",
            "mirror",
            "mirrors"
        ],
        "ans_diff_labels": [
            0,
            0,
            0,
            0,
            4,
            0,
            2,
            2,
            0,
            0
        ],
        "kmeans_score": 62.44444444444444,
        "inertia": 1.4959058989920233e-31,
        "penalty": 44.44444444444444,
        "difference_penalty": 18.0,
        "num_clusters": 5.0,
        "ans_groups": [
            2,
            2,
            4,
            2,
            3,
            2,
            0,
            1,
            0,
            2
        ]
    },
    {
        "qid": "440444003",
        "image": "COCO_train2014_000000440444.jpg",
        "question": "Whose house is this?",
        "src_dataset": "VQA",
        "answers": [
            "don't know",
            "steve's",
            "man",
            "unknown",
            "man's",
            "mom's",
            "model home",
            "tenants",
            "homeowner's",
            "family"
        ],
        "ans_diff_labels": [
            0,
            0,
            0,
            0,
            5,
            1,
            1,
            1,
            0,
            0
        ],
        "kmeans_score": 65.74256660942042,
        "inertia": 17.29812216497598,
        "penalty": 44.44444444444444,
        "difference_penalty": 4.0,
        "num_clusters": 5.0,
        "ans_groups": [
            1,
            3,
            4,
            0,
            2,
            0
        ]
    },
    {
        "qid": "443082002",
        "image": "COCO_train2014_000000443082.jpg",
        "question": "What does the man's shirt say?",
        "src_dataset": "VQA",
        "answers": [
            "eagles",
            "michigan",
            "miami eagles legends, all state champions usa",
            "america beautiful",
            "miami eagles usa",
            "m",
            "can't read it",
            "miami eagles",
            "united",
            "miami eagles"
        ],
        "ans_diff_labels": [
            0,
            1,
            0,
            1,
            3,
            0,
            2,
            2,
            1,
            0
        ],
        "kmeans_score": 86.46146547951167,
        "inertia": 2.683687701733906,
        "penalty": 77.77777777777777,
        "difference_penalty": 6.0,
        "num_clusters": 8.0,
        "ans_groups": [
            7,
            4,
            1,
            6,
            3,
            2,
            0,
            3,
            5,
            3
        ]
    },
    {
        "qid": "441459000",
        "image": "COCO_train2014_000000441459.jpg",
        "question": "What is the woman looking at?",
        "src_dataset": "VQA",
        "answers": [
            "sidewalk",
            "camera",
            "sky",
            "camera",
            "sky",
            "street",
            "street",
            "wall",
            "unknown",
            "photographer"
        ],
        "ans_diff_labels": [
            0,
            1,
            1,
            0,
            4,
            1,
            2,
            2,
            0,
            0
        ],
        "kmeans_score": 72.66666666666667,
        "inertia": 0.0,
        "penalty": 66.66666666666667,
        "difference_penalty": 6.0,
        "num_clusters": 7.0,
        "ans_groups": [
            6,
            1,
            2,
            1,
            2,
            0,
            0,
            5,
            4,
            3
        ]
    },
    {
        "qid": "443497004",
        "image": "COCO_train2014_000000443497.jpg",
        "question": "Why might this skier be involved in some kind of competition?",
        "src_dataset": "VQA",
        "answers": [
            "he isn't",
            "he's wearing tag",
            "because of white pass on his jacket",
            "unsure",
            "tag on jacket",
            "has number",
            "tag",
            "tag on jacket",
            "to try to win",
            "don't think he is"
        ],
        "ans_diff_labels": [
            0,
            1,
            0,
            2,
            3,
            0,
            2,
            2,
            0,
            0
        ],
        "kmeans_score": 87.52556077914889,
        "inertia": 19.970005223593336,
        "penalty": 55.55555555555556,
        "difference_penalty": 12.0,
        "num_clusters": 6.0,
        "ans_groups": [
            1,
            0,
            3,
            2,
            0,
            5,
            4,
            0,
            3,
            3
        ]
    },
    {
        "qid": "442099018",
        "image": "COCO_train2014_000000442099.jpg",
        "question": "What is the wall in the background made of?",
        "src_dataset": "VQA",
        "answers": [
            "drywall",
            "sheetrock",
            "wood",
            "drywall",
            "plaster",
            "white",
            "plaster",
            "concrete",
            "wood",
            "cardboard"
        ],
        "ans_diff_labels": [
            1,
            0,
            0,
            0,
            4,
            0,
            3,
            2,
            1,
            0
        ],
        "kmeans_score": 72.66666666666667,
        "inertia": 0.0,
        "penalty": 66.66666666666667,
        "difference_penalty": 6.0,
        "num_clusters": 7.0,
        "ans_groups": [
            1,
            6,
            3,
            1,
            0,
            2,
            0,
            5,
            3,
            4
        ]
    },
    {
        "qid": "440314001",
        "image": "COCO_train2014_000000440314.jpg",
        "question": "In which direction is the wave moving?",
        "src_dataset": "VQA",
        "answers": [
            "south",
            "forward",
            "right",
            "forward",
            "down",
            "right",
            "toward beach",
            "right",
            "left to right",
            "left"
        ],
        "ans_diff_labels": [
            0,
            1,
            0,
            2,
            4,
            0,
            2,
            2,
            0,
            0
        ],
        "kmeans_score": 71.83952478168148,
        "inertia": 17.39508033723703,
        "penalty": 44.44444444444444,
        "difference_penalty": 10.0,
        "num_clusters": 5.0,
        "ans_groups": [
            3,
            4,
            2,
            4,
            1,
            2,
            1,
            2,
            2,
            0
        ]
    },
    {
        "qid": "442911004",
        "image": "COCO_train2014_000000442911.jpg",
        "question": "What time does it say on the clock?",
        "src_dataset": "VQA",
        "answers": [
            "240",
            "2:40",
            "2:43",
            "2:42",
            "2:40",
            "2:40",
            "240",
            "8:13",
            "2:43",
            "2:40"
        ],
        "ans_diff_labels": [
            0,
            1,
            1,
            1,
            3,
            1,
            1,
            2,
            1,
            0
        ],
        "kmeans_score": 40.96850934431108,
        "inertia": 8.74628712208886,
        "penalty": 22.22222222222222,
        "difference_penalty": 10.0,
        "num_clusters": 3.0,
        "ans_groups": [
            0,
            1,
            2,
            2,
            1,
            1,
            0,
            2,
            2,
            1
        ]
    },
    {
        "qid": "44358000",
        "image": "COCO_train2014_000000044358.jpg",
        "question": "What is the man doing?",
        "src_dataset": "VQA",
        "answers": [
            "filling wine glass",
            "pouring wine",
            "pouring wine",
            "repairing",
            "filling wine glass",
            "pouring wine",
            "filling glass with wine",
            "filling glass",
            "getting drink",
            "looking"
        ],
        "ans_diff_labels": [
            0,
            0,
            0,
            0,
            5,
            0,
            4,
            4,
            0,
            0
        ],
        "kmeans_score": 63.345111731209684,
        "inertia": 4.900667286765239,
        "penalty": 44.44444444444444,
        "difference_penalty": 14.0,
        "num_clusters": 5.0,
        "ans_groups": [
            0,
            1,
            1,
            2,
            0,
            1,
            0,
            0,
            4,
            3
        ]
    }
]
